{
  "cities": {
    "1527": {
      "name": "Tel Aviv",
      "gis": "gisn.tel-aviv.gov.il"
    },
    "1423": {
      "gis": "http://gis.ramat-hasharon.muni.il/RHS/?config=general.xml",
      "displayName": "Ramat Hasharon"
    },
    "1184": {
      "gis": "https://netanyagis.co.il/mobilemap/default.html",
      "displayName": "Netanya"
    },
    "1311": {
      "name": "pardeshananew",
      "gis": "gis01.taldor.co.il",
      "displayName": "Pardes Hanna-Karkur"
    },
    "1371": {
      "name": "KiryatTivonNew",
      "gis": "gis01.taldor.co.il",
      "displayName": "Kiryat Tiv'on"
    },
    "1169": {
      "name": "nesszionanew",
      "gis": "gis03.taldor.co.il",
      "displayName": "Ness Ziona"
    },
    "930": {
      "name": "lodnew",
      "gis": "gis03.taldor.co.il",
      "displayName": "Lod"
    },
    "1434": {
      "name": "raanananew",
      "gis": "gis03.taldor.co.il",
      "displayName": "Ra'anana"
    },
    "1280": {
      "name": "afulanew",
      "gis": "gis04.taldor.co.il",
      "displayName": "Afula"
    },
    "1285": {
      "name": "aradnew",
      "gis": "gis04.taldor.co.il",
      "displayName": "Arad"
    },
    "687": {
      "name": "haderanew",
      "gis": "gis05.taldor.co.il",
      "displayName": "Hadera"
    },
    "397": {
      "name": "efratnew",
      "gis": "gis06.taldor.co.il",
      "displayName": "Efrat"
    },
    "593": {
      "name": "GanYavneNew",
      "gis": "gis06.taldor.co.il",
      "displayName": "Gan Yavne"
    },
    "1417": {
      "name": "RamleGis",
      "gis": "gis06.taldor.co.il",
      "displayName": "Ramle",
      "suffix" :""
    },
    "558": {
      "name": "GivatShmuelNew",
      "gis": "gis07.taldor.co.il"
    },
    "1264": {
      "name": "AkkoNew",
      "gis": "gis07.taldor.co.il"
    },
    "1352": {
      "name": "GalilElionNew",
      "gis": "gis08.taldor.co.il",
      "displayName": "Kadarim"
    },
    "819": {
      "name": "GalilElionNew",
      "gis": "gis08.taldor.co.il",
      "displayName": "Kahal"
    },
    "818": {
      "name": "GalilElionNew",
      "gis": "gis08.taldor.co.il",
      "displayName": "Chorazin"
    },
    "385": {
      "name": "GalilElionNew",
      "gis": "gis08.taldor.co.il",
      "displayName": "Amnun"
    },
    "1272": {
      "name": "GalilElionNew",
      "gis": "gis08.taldor.co.il",
      "displayName": "Ami'ad"
    },
    "911": {
      "name": "GalilElionNew",
      "gis": "gis08.taldor.co.il",
      "displayName": "Karkom"
    },
    "372": {
      "name": "GalilElionNew",
      "gis": "gis08.taldor.co.il",
      "displayName": "Elifelet"
    },
    "856": {
      "name": "GalilElionNew",
      "gis": "gis08.taldor.co.il",
      "displayName": "Kfar HaNassi"
    },
    "991": {
      "name": "GalilElionNew",
      "gis": "gis08.taldor.co.il",
      "displayName": "Mahanayim"
    },
    "1074": {
      "name": "GalilElionNew",
      "gis": "gis08.taldor.co.il",
      "displayName": "Mishmar HaYarden"
    },
    "565": {
      "name": "GalilElionNew",
      "gis": "gis08.taldor.co.il",
      "displayName": "Gadot"
    },
    "348": {
      "name": "GalilElionNew",
      "gis": "gis08.taldor.co.il",
      "displayName": "Ayelet HaShahar"
    },
    "692": {
      "name": "GalilElionNew",
      "gis": "gis08.taldor.co.il",
      "displayName": "Hulata"
    },
    "1449": {
      "name": "GalilElionNew",
      "gis": "gis08.taldor.co.il",
      "displayName": "Sde Eliezer"
    },
    "631": {
      "name": "GalilElionNew",
      "gis": "gis08.taldor.co.il",
      "displayName": "Dishon"
    },
    "1010": {
      "name": "GalilElionNew",
      "gis": "gis08.taldor.co.il",
      "displayName": "Malkia"
    },
    "1416": {
      "name": "GalilElionNew",
      "gis": "gis08.taldor.co.il",
      "displayName": "Ramot Naftali"
    },
    "1016": {
      "name": "GalilElionNew",
      "gis": "gis08.taldor.co.il",
      "displayName": "Manara"
    },
    "789": {
      "name": "GalilElionNew",
      "gis": "gis08.taldor.co.il",
      "displayName": "Yiftah"
    },
    "849": {
      "name": "GalilElionNew",
      "gis": "gis08.taldor.co.il",
      "displayName": "Kfar Giladi"
    },
    "569": {
      "name": "GalilElionNew",
      "gis": "gis08.taldor.co.il",
      "displayName": "Gonen"
    },
    "927": {
      "name": "GalilElionNew",
      "gis": "gis08.taldor.co.il",
      "displayName": "Lehavot HaBashan"
    },
    "842": {
      "name": "GalilElionNew",
      "gis": "gis08.taldor.co.il",
      "displayName": "Kfar Blum"
    },
    "1495": {
      "name": "GalilElionNew",
      "gis": "gis08.taldor.co.il",
      "displayName": "Shamir"
    },
    "1275": {
      "name": "GalilElionNew",
      "gis": "gis08.taldor.co.il",
      "displayName": "Amir"
    },
    "1087": {
      "name": "GalilElionNew",
      "gis": "gis08.taldor.co.il",
      "displayName": "Neot Mordechai"
    },
    "1068": {
      "name": "GalilElionNew",
      "gis": "gis08.taldor.co.il",
      "displayName": "Misgav Am"
    },
    "1032": {
      "name": "GalilElionNew",
      "gis": "gis08.taldor.co.il",
      "displayName": "Ma'ayan Baruch"
    },
    "635": {
      "name": "GalilElionNew",
      "gis": "gis08.taldor.co.il",
      "displayName": "Dan"
    },
    "636": {
      "name": "GalilElionNew",
      "gis": "gis08.taldor.co.il",
      "displayName": "Dafna"
    },
    "1459": {
      "name": "GalilElionNew",
      "gis": "gis08.taldor.co.il",
      "displayName": "Sde Nehemia"
    },
    "641": {
      "name": "GalilElionNew",
      "gis": "gis08.taldor.co.il",
      "displayName": "HaGoshrim"
    },
    "849": {
      "name": "GalilElionNew",
      "gis": "gis08.taldor.co.il",
      "displayName": "Kfar Giladi"
    },
    "446": {
      "name": "GalilElionNew",
      "gis": "gis08.taldor.co.il",
      "displayName": "Beit Hillel"
    },
    "1440": {
      "name": "GalilElionNew",
      "gis": "gis08.taldor.co.il",
      "displayName": "She'ar Yashuv"
    },
    "1499": {
      "name": "GalilElionNew",
      "gis": "gis08.taldor.co.il",
      "displayName": "Snir"
    },
    "2131": {
      "name": "GalilElionNew",
      "gis": "gis08.taldor.co.il",
      "displayName": "Yuval"
    },
    "1093": {
      "name": "naharianew",
      "gis": "gis09.taldor.co.il",
      "displayName": "Naharia"
    },
    "800": {
      "name": "Jerusalem",
      "gis": "https://jergisng.jerusalem.muni.il/baseWab/?config=../gisviewerngsupport/api/InjectingConfig"
    },
    "1390": {
      "name": "Rishonlezion",
      "gis": "v5.gis-net.co.il"
    },
    "1474": {
      "name": "Shoham",
      "gis": "v5.gis-net.co.il"
    },
    "1397": {
      "name": "Rahat",
      "gis": "v5.gis-net.co.il"
    },
    "690": {
      "name": "Holon",
      "gis": "v5.gis-net.co.il"
    },
    "325": {
      "name": "Ofakim",
      "gis": "v5.gis-net.co.il"
    },
    "328": {
      "name": "OrYehuda",
      "gis": "v5.gis-net.co.il"
    },
    "337": {
      "name": "azr",
      "gis": "gis.intertown.co.il",
      "displayName": "Azor"
    },
    "1370": {
      "name": "krg",
      "gis": "gis.intertown.co.il",
      "displayName": "Kiryat Gat"
    },
    "929": {
      "name": "lhv",
      "gis": "gis.intertown.co.il",
      "displayName": "Lehavim"
    },
    "875": {
      "name": "K_Yona",
      "gis": "v5.gis-net.co.il"
    },
    "604": {
      "name": "ganey_tikva",
      "gis": "v5.gis-net.co.il"
    },
    "1178": {
      "name": "Mordot_hacarmel",
      "gis": "v5.gis-net.co.il",
      "displayName": "Nesher"
    },
    "1409": {
      "name": "Mordot_hacarmel",
      "gis": "v5.gis-net.co.il",
      "displayName": "Rekhasim"
    },
    "741": {
      "name": "Mordot_hacarmel",
      "gis": "v5.gis-net.co.il",
      "displayName": "Tirat Carmel"
    },
    "1512": {
      "name": "GvaotAlonim",
      "gis": "v5.gis-net.co.il",
      "displayName": "ShefaAmr"
    },
    "352": {
      "name": "eilat",
      "gis": "v5.gis-net.co.il"
    },
    "412": {
      "name": "ashkelon",
      "gis": "v5.gis-net.co.il"
    },
    "405": {
      "name": "ashdod",
      "gis": "v5.gis-net.co.il"
    },
    "786": {
      "name": "mavo_haamakim",
      "gis": "gis.mavo.co.il",
      "displayName": "Yafia"
    },
    "356": {
      "name": "mavo_haamakim",
      "gis": "gis.mavo.co.il",
      "displayName": "Iksal"
    },
    "1425": {
      "name": "mavo_haamakim",
      "gis": "gis.mavo.co.il",
      "displayName": "Ramat Yishai"
    },
    "879": {
      "name": "mavo_haamakim",
      "gis": "gis.mavo.co.il",
      "displayName": "Kafr Kanna"
    },
    "1069": {
      "name": "mavo_haamakim",
      "gis": "gis.mavo.co.il",
      "displayName": "Mashhad"
    },
    "1229": {
      "name": "mavo_haamakim",
      "gis": "gis.mavo.co.il",
      "displayName": "Ilut"
    },
    "1253": {
      "name": "mavo_haamakim",
      "gis": "gis.mavo.co.il",
      "displayName": "Ein Mahil"
    },
    "1408": {
      "name": "mavo_haamakim",
      "gis": "gis.mavo.co.il",
      "displayName": "Reineh"
    },
    "969": {
      "name": "ModiinGis",
      "prefix": "mod",
      "gis": "gis__prefix__.taldor.co.il",
      "displayName": "Modiin"
    },
    "1387": {
      "name": "Gis/#",
      "prefix": "rh",
      "gis": "gis__prefix__.taldor.co.il",
      "displayName": "Rosh Haayin"
    },
    "891": {
      "name": "KsGis",
      "prefix": "ks",
      "gis": "gis__prefix__.taldor.co.il",
      "displayName": "Kefar Sava"
    },
    "1366": {
      "name": "kono/Default.aspx",
      "gis": "chrome-extension:gis10.taldor.co.il",
      "displayName": "Kiryat Ono"
    },
    "1379": {
      "name": "Kekron_muni/",
      "gis": "chrome-extension:v3.gis-net.co.il",
      "displayName": "Kiryat Ekron"
    },
    "405": {
      "name": "GISNet3/Ashdod/index.htm",
      "gis": "chrome-extension:v3.gis-net.co.il",
      "displayName": "Ashdod"
    },
    "562": {
      "name": "givataim/",
      "gis": "chrome-extension:v3.gis-net.co.il",
      "displayName": "Givataim"
    },
    "1316": {
      "name": "website/gis55/gis-net.asp?citycode=7900",
      "gis": "chrome-extension:gis3.gis-net.co.il",
      "displayName": "Petah Tikva",
      "noExtent": true
    },
    "370": {
      "name": "gisnet/sharonim/",
      "gis": "chrome-extension:v3.gis-net.co.il",
      "displayName": "Elyakhin"
    },
    "304": {
      "name": "gisnet/sharonim/",
      "gis": "chrome-extension:v3.gis-net.co.il",
      "displayName": "Even Yehuda"
    },
    "1312": {
      "name": "gisnet/sharonim/",
      "gis": "chrome-extension:v3.gis-net.co.il",
      "displayName": "Pardesiya"
    },
    "1335": {
      "name": "gisnet/sharonim/",
      "gis": "chrome-extension:v3.gis-net.co.il",
      "displayName": "Kadima Zoran"
    },
    "1530": {
      "name": "gisnet/sharonim/",
      "gis": "chrome-extension:v3.gis-net.co.il",
      "displayName": "Tel Mond"
    },
    "899": {
      "name": "gisnet3/galil_tahton_v4",
      "gis": "v3.gis-net.co.il",
      "displayName": "Kfar Kisch"
    },
    "1468": {
      "name": "gisnet3/galil_tahton_v4",
      "gis": "v3.gis-net.co.il",
      "displayName": "Shadmot Dvora"
    },
    "1515": {
      "name": "gisnet3/galil_tahton_v4",
      "gis": "v3.gis-net.co.il",
      "displayName": "Sarona"
    },
    "1447": {
      "name": "gisnet3/galil_tahton_v4",
      "gis": "v3.gis-net.co.il",
      "displayName": "Sde Ilan"
    },
    "650": {
      "name": "gisnet3/galil_tahton_v4",
      "gis": "v3.gis-net.co.il",
      "displayName": "HaZor'im"
    },
    "398": {
      "name": "gisnet3/galil_tahton_v4",
      "gis": "v3.gis-net.co.il",
      "displayName": "Arbel"
    },
    "924": {
      "name": "gisnet3/galil_tahton_v4",
      "gis": "v3.gis-net.co.il",
      "displayName": "Lavi"
    },
    "1052": {
      "name": "gisnet3/galil_tahton_v4",
      "gis": "v3.gis-net.co.il",
      "displayName": "Mitzpa"
    },
    "866": {
      "name": "gisnet3/galil_tahton_v4",
      "gis": "v3.gis-net.co.il",
      "displayName": "Kfar Hittim"
    },
    "864": {
      "name": "gisnet3/galil_tahton_v4",
      "gis": "v3.gis-net.co.il",
      "displayName": "Kfar Zeitim"
    },
    "1018": {
      "name": "gisnet3/galil_tahton_v4",
      "gis": "v3.gis-net.co.il",
      "displayName": "Masad"
    },
    "1055": {
      "name": "gisnet3/galil_tahton_v4",
      "gis": "v3.gis-net.co.il",
      "displayName": "Mitzpe Netofa"
    },
    "476": {
      "name": "gisnet3/galil_tahton_v4",
      "gis": "v3.gis-net.co.il",
      "displayName": "Beit Rimon"
    },
    "351": {
      "name": "gisnet3/galil_tahton_v4",
      "gis": "v3.gis-net.co.il",
      "displayName": "Ilaniya"
    },
    "474": {
      "name": "gisnet3/galil_tahton_v4",
      "gis": "v3.gis-net.co.il",
      "displayName": "Beit Keshet"
    },
    "811": {
      "name": "gisnet3/galil_tahton_v4",
      "gis": "v3.gis-net.co.il",
      "displayName": "Kadoorie"
    },
    "421": {
      "name": "gisnet3/br7_html5",
      "gis": "v3.gis-net.co.il",
      "displayName": "Be'er Sheva"
    },
    "478": {
      "name": "Beit_Shemesh",
      "gis": "v5.gis-net.co.il"
    },
    "489": {
      "name": "bnei-brak",
      "gis": "v3.gis-net.co.il",
      "displayName": "Bnei Brak"
    },
    "568": {
      "name": "gederagispub",
      "gis": "orhitec.erpgis.co.il",
      "displayName": "Gedera"
    },
    "1470": {
      "name": "sderotgispub",
      "gis": "orhitec.erpgis.co.il",
      "displayName": "Sderot"
    },
    "1365": {
      "name": "qatzringispub",
      "gis": "orhitec.erpgis.co.il",
      "displayName": "Katzrin"
    },
    "891": {
      "name": "Kefar Sava",
      "gis": "https://gisks.taldor.co.il/KsGis"
    },
    "478": {
      "name": "Beit_Shemesh",
      "gis": "v5.gis-net.co.il"
    },
    "522": {
      "name": "batyam",
      "gis": "v5.gis-net.co.il"
    },
    "875": {
      "name": "K_Yona",
      "gis": "v5.gis-net.co.il"
    },
    "690": {
      "name": "Holon",
      "gis": "v5.gis-net.co.il"
    },
    "734": {
      "name": "tiberias",
      "gis": "v5.gis-net.co.il"
    },
    "754": {
      "name": "yavne",
      "gis": "v5.gis-net.co.il"
    },
    "814": {
      "name": "MitzpeAfeq",
      "gis": "v5.gis-net.co.il",
      "displayName": "Kokhav Ya'ir"
    },
    "1329": {
      "name": "MitzpeAfeq",
      "gis": "v5.gis-net.co.il",
      "displayName": "Tzur Yigal"
    },
    "1187": {
      "name": "MitzpeAfeq",
      "gis": "v5.gis-net.co.il",
      "displayName": "Savyon"
    },
    "443": {
      "name": "MitzpeAfeq",
      "gis": "v5.gis-net.co.il",
      "displayName": "Beit Dagan"
    },
    "604": {
      "name": "MitzpeAfeq",
      "gis": "v5.gis-net.co.il",
      "displayName": "Ganei Tikva"
    },
    "420": {
      "name": "MitzpeAfeq",
      "gis": "v5.gis-net.co.il",
      "displayName": "Be'er Ya'akov"
    },
    "1376": {
      "name": "K_Malachi",
      "gis": "v5.gis-net.co.il",
      "displayName": "Kiryat Malakhi"
    },
    "939": {
      "name": "Maale_Hagalil",
      "gis": "v5.gis-net.co.il",
      "displayName": "Lapidot"
    },
    "583": {
      "name": "Maale_Hagalil",
      "gis": "v5.gis-net.co.il",
      "displayName": "Gita"
    },
    "833": {
      "name": "Maale_Hagalil",
      "gis": "v5.gis-net.co.il",
      "displayName": "Kisra-Sume"
    },
    "751": {
      "name": "Maale_Hagalil",
      "gis": "v5.gis-net.co.il",
      "displayName": "Yanuh-Jat"
    },
    "1309": {
      "name": "Maale_Hagalil",
      "gis": "v5.gis-net.co.il",
      "displayName": "Peki'in"
    },
    "694": {
      "name": "Maale_Hagalil",
      "gis": "v5.gis-net.co.il",
      "displayName": "Hosen"
    },
    "862": {
      "name": "Maale_Hagalil",
      "gis": "v5.gis-net.co.il",
      "displayName": "Kfar Vradim"
    },
    "1332": {
      "name": "Maale_Hagalil",
      "gis": "v5.gis-net.co.il",
      "displayName": "Tzuriel"
    },
    "1031": {
      "name": "Maale_Hagalil",
      "gis": "v5.gis-net.co.il",
      "displayName": "Me'ona"
    },
    "1250": {
      "name": "Maale_Hagalil",
      "gis": "v5.gis-net.co.il",
      "displayName": "Ein Ya'akov"
    },
    "381": {
      "name": "Maale_Hagalil",
      "gis": "v5.gis-net.co.il",
      "displayName": "Elkosh"
    },
    "1083": {
      "name": "Maale_Hagalil",
      "gis": "v5.gis-net.co.il",
      "displayName": "Mattat"
    },
    "303": {
      "name": "Maale_Hagalil",
      "gis": "v5.gis-net.co.il",
      "displayName": "Abirim"
    },
    "1139": {
      "name": "Maale_Hagalil",
      "gis": "v5.gis-net.co.il",
      "displayName": "Netu'a"
    },
    "1518": {
      "name": "Maale_Hagalil",
      "gis": "v5.gis-net.co.il",
      "displayName": "Shtula"
    },
    "902": {
      "name": "Maale_Hagalil",
      "gis": "v5.gis-net.co.il",
      "displayName": "Zar'it"
    },
    "1475": {
      "name": "Maale_Hagalil",
      "gis": "v5.gis-net.co.il",
      "displayName": "Shomera"
    },
    "306": {
      "name": "Maale_Hagalil",
      "gis": "v5.gis-net.co.il",
      "displayName": "Even Menachem"
    },
    "571": {
      "name": "Maale_Hagalil",
      "gis": "v5.gis-net.co.il",
      "displayName": "Gornot HaGalil"
    },
    "570": {
      "name": "Maale_Hagalil",
      "gis": "v5.gis-net.co.il",
      "displayName": "Goren"
    },
    "1206": {
      "name": "Maale_Hagalil",
      "gis": "v5.gis-net.co.il",
      "displayName": "Avdon"
    },
    "1014": {
      "name": "Maale_Hagalil",
      "gis": "v5.gis-net.co.il",
      "displayName": "Manot"
    },
    "1106": {
      "name": "Maale_Hagalil",
      "gis": "v5.gis-net.co.il",
      "displayName": "Neve Ziv"
    },
    "1494": {
      "name": "Maale_Hagalil",
      "gis": "v5.gis-net.co.il",
      "displayName": "Shlomi"
    },
    "785": {
      "name": "Maale_Hagalil",
      "gis": "v5.gis-net.co.il",
      "displayName": "Ya'ara"
    },
    "352": {
      "name": "eilat",
      "gis": "v5.gis-net.co.il"
    },
    "1163": {
      "name": "emek_lod",
      "gis": "v5.gis-net.co.il",
      "displayName": "Nir Tzvi"
    },
    "670": {
      "name": "emek_lod",
      "gis": "v5.gis-net.co.il",
      "displayName": "Zeitan"
    },
    "344": {
      "name": "emek_lod",
      "gis": "v5.gis-net.co.il",
      "displayName": "Ahi'ezer"
    },
    "756": {
      "name": "emek_lod",
      "gis": "v5.gis-net.co.il",
      "displayName": "Yagel"
    },
    "865": {
      "name": "emek_lod",
      "gis": "v5.gis-net.co.il",
      "displayName": "Kfar Habad"
    },
    "1339": {
      "name": "emek_lod",
      "gis": "v5.gis-net.co.il",
      "displayName": "Tzafria"
    },
    "710": {
      "name": "emek_lod",
      "gis": "v5.gis-net.co.il",
      "displayName": "Hemed"
    },
    "598": {
      "name": "emek_lod",
      "gis": "v5.gis-net.co.il",
      "displayName": "Ganot"
    },
    "1077": {
      "name": "emek_lod",
      "gis": "v5.gis-net.co.il",
      "displayName": "Mishmar HaShiv'a"
    },
    "1002": {
      "name": "Metar",
      "gis": "v5.gis-net.co.il",
      "displayName": "Meitar"
    },
    "2805": {
      "name": "Metar",
      "gis": "v5.gis-net.co.il",
      "displayName": "Carmit"
    },
    "1341": {
      "name": "Tzafatint",
      "gis": "v5.gis-net.co.il",
      "displayName": "Safed"
    },
    "1035": {
      "name": "Maale_adummim",
      "gis": "v5.gis-net.co.il"
    },
    "1191": {
      "name": "gisnet/galil_mizrahi",
      "gis": "v3.gis-net.co.il",
      "displayName": "Sulam"
    },
    "643": {
      "name": "Hod_hasharon",
      "gis": "v3.gis-net.co.il"
    },
    "662": {
      "name": "Herzliya",
      "gis": "v3.gis-net.co.il"
    },
    "626": {
      "name": "gisnet/galil_mizrahi",
      "gis": "v3.gis-net.co.il",
      "displayName": "Ed Dahi"
    },
    "1143": {
      "name": "gisnet/galil_mizrahi",
      "gis": "v3.gis-net.co.il",
      "displayName": "Nein"
    },
    "886": {
      "name": "gisnet/galil_mizrahi",
      "gis": "v3.gis-net.co.il",
      "displayName": "Kafr Misr"
    },
    "908": {
      "name": "gisnet/galil_mizrahi",
      "gis": "v3.gis-net.co.il",
      "displayName": "Kfar Tavor"
    },
    "1443": {
      "name": "gisnet/galil_mizrahi",
      "gis": "v3.gis-net.co.il",
      "displayName": "Shibli-Umm al-Ghanam"
    },
    "878": {
      "name": "gisnet/galil_mizrahi",
      "gis": "v3.gis-net.co.il",
      "displayName": "Kfar Kama"
    },
    "753": {
      "name": "gisnet/galil_mizrahi",
      "gis": "v3.gis-net.co.il",
      "displayName": "Yavne'el"
    },
    "736": {
      "name": "gisnet/galil_mizrahi",
      "gis": "v3.gis-net.co.il",
      "displayName": "Tur'an"
    },
    "1402": {
      "name": "gisnet/galil_mizrahi",
      "gis": "v3.gis-net.co.il",
      "displayName": "Rumat al-Heib"
    },
    "1401": {
      "name": "gisnet/galil_mizrahi",
      "gis": "v3.gis-net.co.il",
      "displayName": "Rumana"
    },
    "1212": {
      "name": "gisnet/galil_mizrahi",
      "gis": "v3.gis-net.co.il",
      "displayName": "Uzeir"
    },
    "426": {
      "name": "gisnet/galil_mizrahi",
      "gis": "v3.gis-net.co.il",
      "displayName": "Bu'eine Nujeidat"
    },
    "1227": {
      "name": "gisnet/galil_mizrahi",
      "gis": "v3.gis-net.co.il",
      "displayName": "Eilabun"
    },
    "954": {
      "name": "gisnet/galil_mizrahi",
      "gis": "v3.gis-net.co.il",
      "displayName": "Maghar"
    },
    "398": {
      "name": "gisnet/galil_mizrahi",
      "gis": "v3.gis-net.co.il",
      "displayName": "Arbel"
    },
    "956": {
      "name": "gisnet/galil_mizrahi",
      "gis": "v3.gis-net.co.il",
      "displayName": "Migdal"
    },
    "1143": {
      "name": "gisnet/galil_mizrahi",
      "gis": "v3.gis-net.co.il",
      "displayName": "Nein"
    },
    "329": {
      "name": "shomron",
      "gis": "v3.gis-net.co.il",
      "displayName": "Or Akiva"
    },
    "498": {
      "name": "shomron",
      "gis": "v3.gis-net.co.il",
      "displayName": "Binyamina-Giv'at Ada"
    },
    "529": {
      "name": "shomron",
      "gis": "v3.gis-net.co.il",
      "displayName": "Jisr az-Zarqa"
    },
    "795": {
      "name": "yokneam_public",
      "gis": "v3.gis-net.co.il"
    },
    "671": {
      "name": "shomron",
      "gis": "v3.gis-net.co.il",
      "displayName": "Zikhron Ya'akov"
    },
    "1299": {
      "name": "shomron",
      "gis": "v3.gis-net.co.il",
      "displayName": "Fureidis"
    },
    "643": {
      "name": "Hod_hasharon",
      "gis": "v3.gis-net.co.il"
    },
    "662": {
      "name": "Herzliya",
      "gis": "v3.gis-net.co.il"
    },
    "1080": {
      "name": "gisnet3/lev_hasharon",
      "gis": "v3.gis-net.co.il",
      "displayName": "Mishmeret"
    },
    "730": {
      "name": "gisnet3/lev_hasharon",
      "gis": "v3.gis-net.co.il",
      "displayName": "Herut"
    },
    "491": {
      "name": "gisnet3/lev_hasharon",
      "gis": "v3.gis-net.co.il",
      "displayName": "Bnei Dror"
    },
    "857": {
      "name": "gisnet3/lev_hasharon",
      "gis": "v3.gis-net.co.il",
      "displayName": "Kfar Hess"
    },
    "1221": {
      "name": "gisnet3/lev_hasharon",
      "gis": "v3.gis-net.co.il",
      "displayName": "Azri'el"
    },
    "1243": {
      "name": "gisnet3/lev_hasharon",
      "gis": "v3.gis-net.co.il",
      "displayName": "Ein Vered"
    },
    "784": {
      "name": "gisnet3/lev_hasharon",
      "gis": "v3.gis-net.co.il",
      "displayName": "Ye'af"
    },
    "877": {
      "name": "gisnet3/lev_hasharon",
      "gis": "v3.gis-net.co.il",
      "displayName": "Kfar Yavetz"
    },
    "1300": {
      "name": "gisnet3/lev_hasharon",
      "gis": "v3.gis-net.co.il",
      "displayName": "Porat"
    },
    "533": {
      "name": "gisnet3/lev_hasharon",
      "gis": "v3.gis-net.co.il",
      "displayName": "Geulim"
    },
    "1503": {
      "name": "gisnet3/lev_hasharon",
      "gis": "v3.gis-net.co.il",
      "displayName": "Sha'ar Efraim"
    },
    "1148": {
      "name": "gisnet3/lev_hasharon",
      "gis": "v3.gis-net.co.il",
      "displayName": "Nitzanei Oz"
    },
    "1544": {
      "name": "gisnet3/lev_hasharon",
      "gis": "v3.gis-net.co.il",
      "displayName": "Tnuvot"
    },
    "533": {
      "name": "gisnet3/lev_hasharon",
      "gis": "v3.gis-net.co.il",
      "displayName": "Geulim"
    },
    "777": {
      "name": "gisnet3/lev_hasharon",
      "gis": "v3.gis-net.co.il",
      "displayName": "Yanuv"
    },
    "1330": {
      "name": "gisnet3/lev_hasharon",
      "gis": "v3.gis-net.co.il",
      "displayName": "Tzur Moshe"
    },
    "1120": {
      "name": "gisnet3/lev_hasharon",
      "gis": "v3.gis-net.co.il",
      "displayName": "Nordia"
    },
    "599": {
      "name": "gisnet3/lev_hasharon",
      "gis": "v3.gis-net.co.il",
      "displayName": "Ganot Hadar"
    },
    "1260": {
      "name": "gisnet3/lev_hasharon",
      "gis": "v3.gis-net.co.il",
      "displayName": "Ein Sarid"
    },
    "1056": {
      "name": "m_ramon",
      "gis": "v3.gis-net.co.il",
      "displayName": "Mitzpe Ramon"
    },
    "1183": {
      "name": "netivot",
      "gis": "v3.gis-net.co.il"
    },
    "1214": {
      "name": "gisnet/omer",
      "gis": "v3.gis-net.co.il"
    },
    "1405": {
      "name": "gisnet3/rechovot",
      "gis": "v3.gis-net.co.il"
    },
    "1419": {
      "name": "gisnet3/ramat_gan",
      "gis": "v3.gis-net.co.il"
    },
    "705": {
      "name": "haifa_html5",
      "gis": "gis.haifa.muni.il"
    },
    "1177": {
      "name": "GMSC/Public/GMSC_NZIL/NZIL_Community",
      "gis": "metrogis.metropolinet.co.il",
      "displayName": "Nof HaGalil"
    }
  },
  "gis": {
    "gisn.tel-aviv.gov.il": {
      "url": "https://gisn.tel-aviv.gov.il/iView2js4/index.aspx?extent=",
      "functionName": "likeTlv"
    },
    "chrome-extension:v3.gis-net.co.il": {
      "url": "http://v3.gis-net.co.il/",
      "functionName": "v3GisNetChromeExtension"
    },
    "chrome-extension:gis3.gis-net.co.il": {
      "url": "http://gis3.gis-net.co.il/",
      "functionName": "v3GisNetChromeExtension"
    },
    "chrome-extension:gis10.taldor.co.il": {
      "url": "https://gis10.taldor.co.il/",
      "functionName": "v3GisNetChromeExtension"
    },
    "v3.gis-net.co.il": {
      "url": "https://v3.gis-net.co.il/",
      "functionName": "v3GisNet"
    },
    "gis.haifa.muni.il": {
      "url": "http://gis.haifa.muni.il/",
      "functionName": "v3GisNet"
    },
    "v5.gis-net.co.il": {
      "url": "https://v5.gis-net.co.il/v5/",
      "functionName": "v5GisNet"
    },
    "gis.mavo.co.il": {
      "url": "http://gis.mavo.co.il/v5/",
      "functionName": "v5GisNet"
    },
    "gis.intertown.co.il": {
      "url": "https://gis.intertown.co.il/",
      "functionName": "gisIntertown"
    },
    "gis01.taldor.co.il": {
      "url": "https://gis01.taldor.co.il/",
      "functionName": "gis01To09Taldor"
    },
    "gis02.taldor.co.il": {
      "url": "https://gis02.taldor.co.il/",
      "functionName": "gis01To09Taldor"
    },
    "gis03.taldor.co.il": {
      "url": "https://gis03.taldor.co.il/",
      "functionName": "gis01To09Taldor"
    },
    "gis04.taldor.co.il": {
      "url": "https://gis04.taldor.co.il/",
      "functionName": "gis01To09Taldor"
    },
    "gis05.taldor.co.il": {
      "url": "https://gis05.taldor.co.il/",
      "functionName": "gis01To09Taldor"
    },
    "gis06.taldor.co.il": {
      "url": "https://gis06.taldor.co.il/",
      "functionName": "gis01To09Taldor"
    },
    "gis07.taldor.co.il": {
      "url": "https://gis07.taldor.co.il/",
      "functionName": "gis01To09Taldor"
    },
    "gis08.taldor.co.il": {
      "url": "https://gis08.taldor.co.il/",
      "functionName": "gis01To09Taldor"
    },
    "gis09.taldor.co.il": {
      "url": "https://gis09.taldor.co.il/",
      "functionName": "gis01To09Taldor"
    },
    "gis__prefix__.taldor.co.il": {
      "url": "https://gis__prefix__.taldor.co.il/",
      "functionName": "gisTaldorPrefix"
    },
    "orhitec.erpgis.co.il": {
      "url": "https://orhitec.erpgis.co.il/",
      "functionName": "orhitecErpgis"
    },
    "metrogis.metropolinet.co.il": {
      "url": "https://metrogis.metropolinet.co.il/",
      "functionName": "metropolinet"
    }
  }
}
